Workbook

Sheet 封面
B2: 贵州茅台（600519.SH）估值模型
B3: DCF绝对估值（FCFF二阶段）+ 可比公司相对估值 + 敏感性分析
B5: 模型日期 | C5: 2026-10-24
B6: 基准年度 | C6: 2025年年报（官方披露）+ 2026年半年报
B7: 现价（2026-10-22） | C7: 1335
B8: 总股本 | C8: 12.523
B10: 估值结论摘要
B11: DCF每股价值（WACC≈7.2%，g 2.5%） | C11: ='DCF估值'!B33
B12: 可比估值区间（2026E PE 22-26倍） | C12: ='可比估值'!B15
B13: 综合目标区间 | C13: 1,550 – 1,800元（中枢1,700元）
B14: 对应2026E PE | C14: ='DCF估值'!B36
B15: 隐含上行空间（中枢） | C15: =1700/'DCF估值'!B34-1
B17: 颜色图例
B18: 蓝色字体单元格 | C18: 输入假设，可直接修改，全表自动重算
B19: 黑色字体单元格 | C19: 公式自动计算，请勿覆盖
B21: 免责声明：本模型为「研报侠」AI技能生成的估值研究示例，所有数据来自公开渠道，不构成任何投资建议。

Sheet 历史财务
A1: 历史财务数据（2021-2025年报 + 2026中报）
A3: 项目 | B3: 2021A | C3: 2022A | D3: 2023A | E3: 2024A | F3: 2025A | G3: 2026H1
A4: 营业总收入（亿元） | B4: 1094.64 | C4: 1275.54 | D4: 1505.6 | E4: 1741.44 | F4: 1720.54 | G4: 922.78
A5: 同比增速 | B5: 0.1171 | C5: 0.1653 | D5: 0.1804 | E5: 0.1566 | F5: -0.0121 | G5: 0.013
A6: 归母净利润（亿元） | B6: 524.6 | C6: 627.16 | D6: 747.34 | E6: 862.28 | F6: 823.2 | G6: 445.17
A7: 同比增速 | B7: 0.1234 | C7: 0.1955 | D7: 0.1916 | E7: 0.1538 | F7: -0.0453 | G7: -0.0195
A8: EPS（元） | B8: — | C8: — | D8: 59.49 | E8: 68.64 | F8: 65.66 | G8: —
A9: 加权ROE | B9: — | C9: — | D9: 0.3419 | E9: 0.3602 | F9: 0.3253 | G9: —
A10: 经营现金流净额（亿元） | B10: — | C10: — | D10: 665.93 | E10: 924.64 | F10: 615.22 | G10: —
A11: 全年现金分红总额（亿元） | B11: — | C11: — | D11: — | E11: 646.7 | F11: 650.33 | G11: —
A13: 注：营业总收入=营业收入+利息收入等；2025年为上市以来首次营收净利双下滑；2026H1归母净利-1.95%。
A14: 来源：贵州茅台2025年年度报告（官方PDF）、2026年半年报；详见《假设与说明》页。

Sheet 盈利预测
A1: 盈利预测（2026E-2030E）
A2: 全部由蓝色假设驱动；茅台酒/系列酒/其他三条线独立预测后加总。
A3: 项目 | B3: 2025A | C3: 2026E | D3: 2027E | E3: 2028E | F3: 2029E | G3: 2030E
A4: 茅台酒收入增速 | B4: 0.0039 | C4: 0.04 | D4: 0.062 | E4: 0.055 | F4: 0.045 | G4: 0.035
A5: 茅台酒收入（亿元） | B5: 1465 | C5: =B5*(1+C4) | D5: =C5*(1+D4) | E5: =D5*(1+E4) | F5: =E5*(1+F4) | G5: =F5*(1+G4)
A6: 系列酒收入增速 | B6: -0.0976 | C6: 0.02 | D6: 0.06 | E6: 0.07 | F6: 0.058 | G6: 0.05
A7: 系列酒收入（亿元） | B7: 222.75 | C7: =B7*(1+C6) | D7: =C7*(1+D6) | E7: =D7*(1+E6) | F7: =E7*(1+F6) | G7: =F7*(1+G6)
A8: 其他收入增速（利息等） | B8: — | C8: 0.006 | D8: 0.03 | E8: 0.03 | F8: 0.03 | G8: 0.03
A9: 其他收入（亿元） | B9: 32.79 | C9: =B9*(1+C8) | D9: =C9*(1+D8) | E9: =D9*(1+E8) | F9: =E9*(1+F8) | G9: =F9*(1+G8)
A10: 营业总收入（亿元） | B10: =B5+B7+B9 | C10: =C5+C7+C9 | D10: =D5+D7+D9 | E10: =E5+E7+E9 | F10: =F5+F7+F9 | G10: =G5+G7+G9
A11: 收入同比 | B11: =B10/A10-1 | C11: =C10/B10-1 | D11: =D10/C10-1 | E11: =E10/D10-1 | F11: =F10/E10-1 | G11: =G10/F10-1
A12: 归母净利率 | B12: 0.4784 | C12: 0.48 | D12: 0.492 | E12: 0.495 | F12: 0.497 | G12: 0.498
A13: 归母净利润（亿元） | B13: 823.2 | C13: =C10*C12 | D13: =D10*D12 | E13: =E10*E12 | F13: =F10*F12 | G13: =G10*G12
A14: 净利同比 | B14: =B13/A13-1 | C14: =C13/B13-1 | D14: =D13/C13-1 | E14: =E13/D13-1 | F14: =F13/E13-1 | G14: =G13/F13-1
A15: 总股本（亿股） | B15: 12.523
A16: EPS（元） | B16: =B13/$B$15 | C16: =C13/$B$15 | D16: =D13/$B$15 | E16: =E13/$B$15 | F16: =F13/$B$15 | G16: =G13/$B$15
A18: 关键假设依据：
A19: 1. 2026E茅台酒+4.0%：H1实际持平（777亿），H2提价满效应+2025H2控货低基数
A20: 2. 提价传导：出厂价1169→1269元(+8.6%)自2026-03-31生效，出厂价增利未计入7月i茅台二次上调
A21: 3. 系列酒2026E+2%为结构调整尾声，2027年起随行业回暖恢复
A22: 4. 其他（财务公司利息收入等）低个位数稳态增长
A23: 5. 提价结构性增利+直销占比提升 > 销售费用'全面向C'投入（2026E销售费用假设+12%）
A24: 注：EPS按期末股本计算，与年报加权平均口径差异<0.2%。

Sheet DCF估值
A1: DCF估值（FCFF二阶段模型）
A3: 折现率假设
A4: 无风险利率 Rf（10Y国债） | B4: 0.0164
A5: 股权风险溢价 ERP | B5: 0.065
A6: Beta（白酒防御属性） | B6: 0.85
A7: WACC = Rf + β×ERP（≈Ke，全股权） | B7: =B4+B5*B6
A8: 永续增长率 g | B8: 0.025
A9: 超额净现金（亿元） | B9: 1300
A10: 少数股东权益（亿元） | B10: 30
A11: 总股本（亿股） | B11: =盈利预测!B15
A13: FCFF预测（亿元）
A14: 项目 | B14: 2026E | C14: 2027E | D14: 2028E | E14: 2029E | F14: 2030E
A15: 归母净利润（引用盈利预测） | B15: ='盈利预测'!B13 | C15: ='盈利预测'!C13 | D15: ='盈利预测'!D13 | E15: ='盈利预测'!E13 | F15: ='盈利预测'!F13
A16: 少数股东损益还原 +1.5% | B16: 0.015 | C16: 0.015 | D16: 0.015 | E16: 0.015 | F16: 0.015
A17: NOPAT = 净利×(1+少数占比) | B17: =B15*(1+B16) | C17: =C15*(1+C16) | D17: =D15*(1+D16) | E17: =E15*(1+E16) | F17: =F15*(1+F16)
A18: 折旧摊销（+） | B18: 30 | C18: 32 | D18: 35 | E18: 37 | F18: 38
A19: 资本开支（−） | B19: 60 | C19: 55 | D19: 50 | E19: 45 | F19: 40
A20: 营运资金变动（−） | B20: 0 | C20: 0 | D20: 0 | E20: 0 | F20: 0
A21: FCFF | B21: =B17+B18-B19-B20 | C21: =C17+C18-C19-C20 | D21: =D17+D18-D19-D20 | E21: =E17+E18-E19-E20 | F21: =F17+F18-F19-F20
A22: 折现期 t（年） | B22: 1 | C22: 2 | D22: 3 | E22: 4 | F22: 5
A23: 折现因子 =1/(1+WACC)^t | B23: =1/(1+$B$7)^B22 | C23: =1/(1+$B$7)^C22 | D23: =1/(1+$B$7)^D22 | E23: =1/(1+$B$7)^E22 | F23: =1/(1+$B$7)^F22
A24: FCFF现值 | B24: =B21*B23 | C24: =C21*C23 | D24: =D21*D23 | E24: =E21*E23 | F24: =F21*F23
A26: 显性期FCFF现值合计（亿元） | B26: =SUM(C24:G24)
A27: 终值 TV = FCFF2030×(1+g)/(WACC−g) | B27: =G21*(1+B8)/(B7-B8)
A28: 终值现值 | B28: =B27*G23
A29: 企业价值 EV | B29: =B26+B28
A30: 加：超额净现金 | B30: =B9
A31: 减：少数股东权益 | B31: =B10
A32: 股权价值（亿元） | B32: =B29+B30-B31
A33: 每股价值（元） | B33: =B32/B11
A34: 现价（元，2026-10-22） | B34: 1335
A35: 隐含上行空间 | B35: =B33/B34-1
A36: 对应2026E PE | B36: =B33/'盈利预测'!C16
A39: 注：WACC行(第7行)由Rf+β×ERP计算；引用单元格：B4=Rf, B5=ERP, B6=β, B7=WACC, B8=g, B9=净现金, B10=少数, B11=股本。

Sheet 敏感性分析
A1: 敏感性分析：每股价值（元） = f（WACC，永续增长率g）
A2: 矩阵公式内嵌完整DCF：修改左侧/顶部蓝色假设或DCF页FCFF后自动重算。
A4: WACC \ g | B4: 0.02 | C4: 0.0225 | D4: 0.025 | E4: 0.0275 | F4: 0.03
A5: 0.062 | B5: =('DCF估值'!B21/(1+$A5)^1+'DCF估值'!C21/(1+$A5)^2+'DCF估值'!D21/(1+$A5)^3+'DCF估值'!E21/(1+$A5)^4+'DCF估值'!F21/(1+$A5)^5+'DCF估值'!G21*(1+B$4)/($A5-B$4)/(1+$A5)^5+'DCF估值'!$B$9-'DCF估值'!$B$10)/'DCF估值'!$B$11 | C5: =('DCF估值'!B21/(1+$A5)^1+'DCF估值'!C21/(1+$A5)^2+'DCF估值'!D21/(1+$A5)^3+'DCF估值'!E21/(1+$A5)^4+'DCF估值'!F21/(1+$A5)^5+'DCF估值'!G21*(1+C$4)/($A5-C$4)/(1+$A5)^5+'DCF估值'!$B$9-'DCF估值'!$B$10)/'DCF估值'!$B$11 | D5: =('DCF估值'!B21/(1+$A5)^1+'DCF估值'!C21/(1+$A5)^2+'DCF估值'!D21/(1+$A5)^3+'DCF估值'!E21/(1+$A5)^4+'DCF估值'!F21/(1+$A5)^5+'DCF估值'!G21*(1+D$4)/($A5-D$4)/(1+$A5)^5+'DCF估值'!$B$9-'DCF估值'!$B$10)/'DCF估值'!$B$11 | E5: =('DCF估值'!B21/(1+$A5)^1+'DCF估值'!C21/(1+$A5)^2+'DCF估值'!D21/(1+$A5)^3+'DCF估值'!E21/(1+$A5)^4+'DCF估值'!F21/(1+$A5)^5+'DCF估值'!G21*(1+E$4)/($A5-E$4)/(1+$A5)^5+'DCF估值'!$B$9-'DCF估值'!$B$10)/'DCF估值'!$B$11 | F5: =('DCF估值'!B21/(1+$A5)^1+'DCF估值'!C21/(1+$A5)^2+'DCF估值'!D21/(1+$A5)^3+'DCF估值'!E21/(1+$A5)^4+'DCF估值'!F21/(1+$A5)^5+'DCF估值'!G21*(1+F$4)/($A5-F$4)/(1+$A5)^5+'DCF估值'!$B$9-'DCF估值'!$B$10)/'DCF估值'!$B$11
A6: 0.067 | B6: =('DCF估值'!B21/(1+$A6)^1+'DCF估值'!C21/(1+$A6)^2+'DCF估值'!D21/(1+$A6)^3+'DCF估值'!E21/(1+$A6)^4+'DCF估值'!F21/(1+$A6)^5+'DCF估值'!G21*(1+B$4)/($A6-B$4)/(1+$A6)^5+'DCF估值'!$B$9-'DCF估值'!$B$10)/'DCF估值'!$B$11 | C6: =('DCF估值'!B21/(1+$A6)^1+'DCF估值'!C21/(1+$A6)^2+'DCF估值'!D21/(1+$A6)^3+'DCF估值'!E21/(1+$A6)^4+'DCF估值'!F21/(1+$A6)^5+'DCF估值'!G21*(1+C$4)/($A6-C$4)/(1+$A6)^5+'DCF估值'!$B$9-'DCF估值'!$B$10)/'DCF估值'!$B$11 | D6: =('DCF估值'!B21/(1+$A6)^1+'DCF估值'!C21/(1+$A6)^2+'DCF估值'!D21/(1+$A6)^3+'DCF估值'!E21/(1+$A6)^4+'DCF估值'!F21/(1+$A6)^5+'DCF估值'!G21*(1+D$4)/($A6-D$4)/(1+$A6)^5+'DCF估值'!$B$9-'DCF估值'!$B$10)/'DCF估值'!$B$11 | E6: =('DCF估值'!B21/(1+$A6)^1+'DCF估值'!C21/(1+$A6)^2+'DCF估值'!D21/(1+$A6)^3+'DCF估值'!E21/(1+$A6)^4+'DCF估值'!F21/(1+$A6)^5+'DCF估值'!G21*(1+E$4)/($A6-E$4)/(1+$A6)^5+'DCF估值'!$B$9-'DCF估值'!$B$10)/'DCF估值'!$B$11 | F6: =('DCF估值'!B21/(1+$A6)^1+'DCF估值'!C21/(1+$A6)^2+'DCF估值'!D21/(1+$A6)^3+'DCF估值'!E21/(1+$A6)^4+'DCF估值'!F21/(1+$A6)^5+'DCF估值'!G21*(1+F$4)/($A6-F$4)/(1+$A6)^5+'DCF估值'!$B$9-'DCF估值'!$B$10)/'DCF估值'!$B$11
A7: 0.072 | B7: =('DCF估值'!B21/(1+$A7)^1+'DCF估值'!C21/(1+$A7)^2+'DCF估值'!D21/(1+$A7)^3+'DCF估值'!E21/(1+$A7)^4+'DCF估值'!F21/(1+$A7)^5+'DCF估值'!G21*(1+B$4)/($A7-B$4)/(1+$A7)^5+'DCF估值'!$B$9-'DCF估值'!$B$10)/'DCF估值'!$B$11 | C7: =('DCF估值'!B21/(1+$A7)^1+'DCF估值'!C21/(1+$A7)^2+'DCF估值'!D21/(1+$A7)^3+'DCF估值'!E21/(1+$A7)^4+'DCF估值'!F21/(1+$A7)^5+'DCF估值'!G21*(1+C$4)/($A7-C$4)/(1+$A7)^5+'DCF估值'!$B$9-'DCF估值'!$B$10)/'DCF估值'!$B$11 | D7: =('DCF估值'!B21/(1+$A7)^1+'DCF估值'!C21/(1+$A7)^2+'DCF估值'!D21/(1+$A7)^3+'DCF估值'!E21/(1+$A7)^4+'DCF估值'!F21/(1+$A7)^5+'DCF估值'!G21*(1+D$4)/($A7-D$4)/(1+$A7)^5+'DCF估值'!$B$9-'DCF估值'!$B$10)/'DCF估值'!$B$11 | E7: =('DCF估值'!B21/(1+$A7)^1+'DCF估值'!C21/(1+$A7)^2+'DCF估值'!D21/(1+$A7)^3+'DCF估值'!E21/(1+$A7)^4+'DCF估值'!F21/(1+$A7)^5+'DCF估值'!G21*(1+E$4)/($A7-E$4)/(1+$A7)^5+'DCF估值'!$B$9-'DCF估值'!$B$10)/'DCF估值'!$B$11 | F7: =('DCF估值'!B21/(1+$A7)^1+'DCF估值'!C21/(1+$A7)^2+'DCF估值'!D21/(1+$A7)^3+'DCF估值'!E21/(1+$A7)^4+'DCF估值'!F21/(1+$A7)^5+'DCF估值'!G21*(1+F$4)/($A7-F$4)/(1+$A7)^5+'DCF估值'!$B$9-'DCF估值'!$B$10)/'DCF估值'!$B$11
A8: 0.077 | B8: =('DCF估值'!B21/(1+$A8)^1+'DCF估值'!C21/(1+$A8)^2+'DCF估值'!D21/(1+$A8)^3+'DCF估值'!E21/(1+$A8)^4+'DCF估值'!F21/(1+$A8)^5+'DCF估值'!G21*(1+B$4)/($A8-B$4)/(1+$A8)^5+'DCF估值'!$B$9-'DCF估值'!$B$10)/'DCF估值'!$B$11 | C8: =('DCF估值'!B21/(1+$A8)^1+'DCF估值'!C21/(1+$A8)^2+'DCF估值'!D21/(1+$A8)^3+'DCF估值'!E21/(1+$A8)^4+'DCF估值'!F21/(1+$A8)^5+'DCF估值'!G21*(1+C$4)/($A8-C$4)/(1+$A8)^5+'DCF估值'!$B$9-'DCF估值'!$B$10)/'DCF估值'!$B$11 | D8: =('DCF估值'!B21/(1+$A8)^1+'DCF估值'!C21/(1+$A8)^2+'DCF估值'!D21/(1+$A8)^3+'DCF估值'!E21/(1+$A8)^4+'DCF估值'!F21/(1+$A8)^5+'DCF估值'!G21*(1+D$4)/($A8-D$4)/(1+$A8)^5+'DCF估值'!$B$9-'DCF估值'!$B$10)/'DCF估值'!$B$11 | E8: =('DCF估值'!B21/(1+$A8)^1+'DCF估值'!C21/(1+$A8)^2+'DCF估值'!D21/(1+$A8)^3+'DCF估值'!E21/(1+$A8)^4+'DCF估值'!F21/(1+$A8)^5+'DCF估值'!G21*(1+E$4)/($A8-E$4)/(1+$A8)^5+'DCF估值'!$B$9-'DCF估值'!$B$10)/'DCF估值'!$B$11 | F8: =('DCF估值'!B21/(1+$A8)^1+'DCF估值'!C21/(1+$A8)^2+'DCF估值'!D21/(1+$A8)^3+'DCF估值'!E21/(1+$A8)^4+'DCF估值'!F21/(1+$A8)^5+'DCF估值'!G21*(1+F$4)/($A8-F$4)/(1+$A8)^5+'DCF估值'!$B$9-'DCF估值'!$B$10)/'DCF估值'!$B$11
A9: 0.082 | B9: =('DCF估值'!B21/(1+$A9)^1+'DCF估值'!C21/(1+$A9)^2+'DCF估值'!D21/(1+$A9)^3+'DCF估值'!E21/(1+$A9)^4+'DCF估值'!F21/(1+$A9)^5+'DCF估值'!G21*(1+B$4)/($A9-B$4)/(1+$A9)^5+'DCF估值'!$B$9-'DCF估值'!$B$10)/'DCF估值'!$B$11 | C9: =('DCF估值'!B21/(1+$A9)^1+'DCF估值'!C21/(1+$A9)^2+'DCF估值'!D21/(1+$A9)^3+'DCF估值'!E21/(1+$A9)^4+'DCF估值'!F21/(1+$A9)^5+'DCF估值'!G21*(1+C$4)/($A9-C$4)/(1+$A9)^5+'DCF估值'!$B$9-'DCF估值'!$B$10)/'DCF估值'!$B$11 | D9: =('DCF估值'!B21/(1+$A9)^1+'DCF估值'!C21/(1+$A9)^2+'DCF估值'!D21/(1+$A9)^3+'DCF估值'!E21/(1+$A9)^4+'DCF估值'!F21/(1+$A9)^5+'DCF估值'!G21*(1+D$4)/($A9-D$4)/(1+$A9)^5+'DCF估值'!$B$9-'DCF估值'!$B$10)/'DCF估值'!$B$11 | E9: =('DCF估值'!B21/(1+$A9)^1+'DCF估值'!C21/(1+$A9)^2+'DCF估值'!D21/(1+$A9)^3+'DCF估值'!E21/(1+$A9)^4+'DCF估值'!F21/(1+$A9)^5+'DCF估值'!G21*(1+E$4)/($A9-E$4)/(1+$A9)^5+'DCF估值'!$B$9-'DCF估值'!$B$10)/'DCF估值'!$B$11 | F9: =('DCF估值'!B21/(1+$A9)^1+'DCF估值'!C21/(1+$A9)^2+'DCF估值'!D21/(1+$A9)^3+'DCF估值'!E21/(1+$A9)^4+'DCF估值'!F21/(1+$A9)^5+'DCF估值'!G21*(1+F$4)/($A9-F$4)/(1+$A9)^5+'DCF估值'!$B$9-'DCF估值'!$B$10)/'DCF估值'!$B$11
A11: 对应上行空间（相对现价）
A12: 0.062 | B12: =B5/'DCF估值'!$B$34-1 | C12: =C5/'DCF估值'!$B$34-1 | D12: =D5/'DCF估值'!$B$34-1 | E12: =E5/'DCF估值'!$B$34-1 | F12: =F5/'DCF估值'!$B$34-1
A13: 0.067 | B13: =B6/'DCF估值'!$B$34-1 | C13: =C6/'DCF估值'!$B$34-1 | D13: =D6/'DCF估值'!$B$34-1 | E13: =E6/'DCF估值'!$B$34-1 | F13: =F6/'DCF估值'!$B$34-1
A14: 0.072 | B14: =B7/'DCF估值'!$B$34-1 | C14: =C7/'DCF估值'!$B$34-1 | D14: =D7/'DCF估值'!$B$34-1 | E14: =E7/'DCF估值'!$B$34-1 | F14: =F7/'DCF估值'!$B$34-1
A15: 0.077 | B15: =B8/'DCF估值'!$B$34-1 | C15: =C8/'DCF估值'!$B$34-1 | D15: =D8/'DCF估值'!$B$34-1 | E15: =E8/'DCF估值'!$B$34-1 | F15: =F8/'DCF估值'!$B$34-1
A16: 0.082 | B16: =B9/'DCF估值'!$B$34-1 | C16: =C9/'DCF估值'!$B$34-1 | D16: =D9/'DCF估值'!$B$34-1 | E16: =E9/'DCF估值'!$B$34-1 | F16: =F9/'DCF估值'!$B$34-1
A18: 解读：现价1,335元低于最保守角落（WACC 8.2%×g 2.0%）的每股价值，意味着市场已计入接近永久性衰退的预期。

Sheet 可比估值
A1: 可比公司相对估值
A3: 公司 | B3: PE-TTM | C3: 股息率 | D3: 备注
A4: 贵州茅台 | B4: 19.6 | C4: 0.039 | D4: PE-TTM处近十年2.3%分位
A5: 五粮液 | B5: 15 | C5: 0.073 | D5: 2025年报表口径调整放大降幅
A6: 泸州老窖 | B6: 14 | C6: 0.082 | D6: 2026H1净利-36%
A7: 山西汾酒 | B7: 14 | C7: 0.055 | D7: 2026H1净利-24%
A9: 目标倍数推导（质量调整）
A10: 目标PE下限（2026E） | B10: 22
A11: 目标PE上限（2026E） | B11: 26
A12: 2026E EPS（元） | B12: ='盈利预测'!C16
A13: 可比法每股价值下限 | B13: =B10*B12
A14: 可比法每股价值上限 | B14: =B11*B12
A15: 可比法区间（显示） | B15: =TEXT(B13,"#,##0")&" – "&TEXT(B14,"#,##0")&"元"
A17: 逻辑：可比组14-15倍为盈利受损年份的被动低倍数；茅台以ROE(32.5% vs 同业15-30%)、盈利确定性、79%分红率获得溢价，给予22-26倍（自身历史P30-P50分位），中枢对应DCF结果交叉验证。
A19: 综合估值结论
A20: DCF每股价值 | B20: ='DCF估值'!B33
A21: 可比法区间 | B21: =B15
A22: 综合目标区间 | B22: 1,550 – 1,800元（中枢1,700元）
A23: 现价 | B23: ='DCF估值'!B34
A24: 中枢隐含空间 | B24: =1700/'DCF估值'!B34-1

Sheet 假设与说明
A1: 假设清单、数据来源与免责声明
A3: 一、关键假设及依据
A4: 1. 收入预测：茅台酒2026E+4.0%（H1持平、H2提价满效应+低基数），2027-2030年6.2%/5.5%/4.5%/3.5%递减；系列酒2026E+2%后恢复中高个位数。
A5: 2. 提价传导：飞天出厂价2026-03-31由1169元上调至1269元(+8.6%)，2026-07-18 i茅台零售价1539→1639元；模型仅计入3月出厂价提价，7月二次上调为上行期权。
A6: 3. 净利率48.0%→49.8%：提价与直销结构（直销吨价约为批发3倍）增利大于'全面向C'费用投入（2026E销售费用+12%）。
A7: 4. WACC=7.2%：Rf 1.64%（10Y国债，2026-10-23中债曲线）+β0.85×ERP6.5%；茅台无有息负债，WACC≈Ke。
A8: 5. 永续增长率g=2.5%：不高于长期名义GDP增速，反映行业缩量的克制假设。
A9: 6. 资本开支60→40亿元：茅台酒'十四五'技改(155亿)+3万吨系列酒技改(102亿)+习水同民坝(41亿)建设高峰后递减。
A10: 7. 超额净现金1,300亿元：货币资金+财务公司类现金剔除对应吸收存款后的保守估计，单独加回不参与折现。
A12: 二、主要数据来源
A13: [S1] 贵州茅台2025年年度报告（官方PDF，2026-04-17）
A14: [S2] 贵州茅台2026年第一季度报告（2026-04-27）
... A23: 本模型由「研报侠」AI技能（个人AI投研工作台）生成，为支付宝AI付PAYATHON 2026参赛作品示例。所有数据来自公开渠道，可能存在滞后或口径差异；估值为基于假设的情景推演，不构成任何投资建议。市场有风险，投资需谨慎。

Sheet PY校验值
A1: rev_2026 | B1: 1783.7917
A2: rev_2030 | B2: 2169.7111
A3: np_2026 | B3: 856.22004
A4: np_2030 | B4: 1080.5161
A5: eps_2026 | B5: 68.371799
A6: wacc | B6: 0.07165
A7: fcff_2026 | B7: 839.06334
A8: fcff_2030 | B8: 1094.7239
A9: pv_explicit | B9: 3959.0438
A10: pv_tv | B10: 17018.135
A11: ev | B11: 20977.179
A12: equity | B12: 22247.179
... A16: upside | B16: 0.330716
